veloxml/__init__.py
veloxml/pca/__init__.py
veloxml/pca/pca.py
veloxml/tree/random_forest_classification.py
veloxml/tree/__init__.py
veloxml/tree/decision_tree_classification.py
veloxml/core/c_veloxml_core.cpython-312-darwin.so
veloxml/core/__init__.py
veloxml/linear/lasso_regression.py
veloxml/linear/__init__.py
veloxml/linear/logistic_regression.py
veloxml/linear/elasticnet_regression.py
veloxml/linear/linear_regression.py
veloxml/linear/ridge_regression.py
veloxml/.dylibs/libstdc++.6.dylib
veloxml/.dylibs/libopenblasp-r0.3.29.dylib
veloxml/.dylibs/libgfortran.5.dylib
veloxml/.dylibs/libtbb.12.14.dylib
veloxml/.dylibs/libquadmath.0.dylib
veloxml/svm/__init__.py
veloxml/svm/svm_classification.py
veloxml/base/unsupervised_base.py
veloxml/base/classification_base.py
veloxml/base/regression_base.py
veloxml/base/__init__.py
veloxml/base/estimator_base.py
veloxml/kmeans/__init__.py
veloxml/kmeans/kmeans.py
veloxml-0.0.1.dist-info/RECORD
veloxml-0.0.1.dist-info/LICENSE
veloxml-0.0.1.dist-info/WHEEL
veloxml-0.0.1.dist-info/top_level.txt
veloxml-0.0.1.dist-info/METADATA
