Metadata-Version: 2.2
Name: veloxml
Version: 0.0.1
Summary: High-Performance Machine Learning Library for Python (Powered by C++)
Author: Yuji Chinen
Author-email: Yuji Chinen <veloxml1113@gmail.com>
License: MIT License
Project-URL: Homepage, https://github.com/veloxml/VeloxML
Project-URL: Documentation, https://veloxml.github.io/VeloxML/
Project-URL: Repository, https://github.com/veloxml/VeloxML
Project-URL: Issues, https://github.com/veloxml/VeloxML/issues
Keywords: veloxml,machine-learning,high-performance,python,cpp
Classifier: Development Status :: 3 - Alpha
Classifier: Intended Audience :: Developers
Classifier: License :: OSI Approved :: MIT License
License-File: LICENSE
Requires-Dist: numpy
Requires-Dist: pybind11
Provides-Extra: dev
Requires-Dist: pytest; extra == "dev"
Requires-Dist: sphinx; extra == "dev"
Dynamic: author
